pregex/__init__.py
pregex/core/__init__.py
pregex/core/assertions.py
pregex/core/classes.py
pregex/core/exceptions.py
pregex/core/groups.py
pregex/core/operators.py
pregex/core/pre.py
pregex/core/quantifiers.py
pregex/core/tokens.py
pregex/meta/__init__.py
pregex/meta/essentials.py
pregex-2.3.3.dist-info/LICENSE
pregex-2.3.3.dist-info/METADATA
pregex-2.3.3.dist-info/WHEEL
pregex-2.3.3.dist-info/top_level.txt
pregex-2.3.3.dist-info/RECORD
