Metadata-Version: 2.1
Name: pregex
Version: 2.3.3
Summary: PRegEx - Programmable Regular Expressions
Author: Manos Stoumpos
Author-email: manosstoumpos@gmail.com
License: MIT
Project-URL: Homepage, https://github.com/manoss96/pregex
Project-URL: Bug Tracker, https://github.com/manoss96/pregex/issues
Project-URL: Documentation, https://pregex.rtfd.io
Keywords: regex
Classifier: Programming Language :: Python :: 3
Classifier: License :: OSI Approved :: MIT License
Classifier: Operating System :: OS Independent
Requires-Python: >=3.9
License-File: LICENSE
